{"lvyJTSkxXTmXMI2fjksUaw==":"background-1028x579.jpeg","i8rwG2skakIO8KiNylaK7Q==":"logopit-1583285580903-536x536.jpg","aKtkEi8RJ+AMoLZ9fzIFGQ==":"background%20home-1000x1078.jpeg","0oWAbYUqWdrlzh684uRR+A==":"background%20home-1000x1078.jpeg","IXETXVKuERaiQLV2qL55rQ==":"background-1028x579.jpg","U+b/nsPsOS26L9P5ixtbnw==":"round%20pillows%20(service)%201-696x391.jpeg","f9rJxqQ+0dL+WP8BhE42pQ==":"square%20pillows%20(service)%202-696x522.jpeg","qCTG7Xx7Tz3EqbjWR7v+2A==":"for%20sala%20set%20(service)%203-696x522.jpeg","0dxkKGH84t111rDgI3fMKA==":"2nd%20background%20in%20service-1170x781.jpeg","9Ko0wMgoXlPYM7x3zmiSaA==":"background-1-1028x579.jpeg","zxdmM2OSUmcvUymlq8tjgg==":"2nd%20background%20in%20service-1170x781.jpeg","MVTBEDjqdMt4TesowR5H0g==":"background-2-1028x579.jpeg","w73yoG/W0WPT+pQhzyuaBA==":"other%20designs%204-696x522.jpeg","vDLrtOBZRHyUisBaSJpn0g==":"other%20design%205-696x522.jpeg","GpeoNtoRpJp9AaR6dEWPMg==":"other%20design%206-696x522.jpeg","cSPWwEBcyI/StY+5zL7s/w==":"other%20design%207-696x522.jpeg","RiUkxRM0GxeTFZyzA/R4Ag==":"other%20design%208-696x522.jpeg","eht0ZMdNx161D2zrok5//A==":"other%20design%209-696x928.jpeg","Amf0dBrGcVK9t2nkY0EHKw==":"mv-712x534.jpeg","07RWFJyJuPwsaRx1XyifLA==":"background%20home-1000x1078.jpeg"}